pysemble/__init__.py
pysemble/archivers.py
pysemble/builders.py
pysemble/compilers.py
pysemble/lists/__init__.py
pysemble/lists/helpers.py
pysemble/logger/__init__.py
pysemble/logger/log.py
pysemble-0.0.8.dist-info/LICENSE
pysemble-0.0.8.dist-info/METADATA
pysemble-0.0.8.dist-info/WHEEL
pysemble-0.0.8.dist-info/top_level.txt
pysemble-0.0.8.dist-info/RECORD
