Metadata-Version: 2.1
Name: pysemble
Version: 0.0.8
Summary: C/C++ build system
Home-page: https://github.com/jackdelahunt/Peach
Author: Jack Delahunt
Author-email: jdealhunt@gmail.com
License: MIT
Project-URL: Bug Tracker, https://github.com/jackdelahunt/Peach/issues
Platform: UNKNOWN
Classifier: Programming Language :: Python :: 3
Classifier: License :: OSI Approved :: MIT License
Classifier: Operating System :: OS Independent
Requires-Python: >=3.6
License-File: LICENSE
